{
  "main": {
    "id": "b042173a2ec447db",
    "type": "split",
    "children": [
      {
        "id": "43326fc6301d8918",
        "type": "tabs",
        "children": [
          {
            "id": "3f276d0fd7dabbaa",
            "type": "leaf",
            "state": {
              "type": "markdown",
              "state": {
                "file": "README.md",
                "mode": "source",
                "source": false
              },
              "icon": "lucide-file",
              "title": "README"
            }
          },
          {
            "id": "123e64516c662e9b",
            "type": "leaf",
            "state": {
              "type": "markdown",
              "state": {
                "file": "A_INSPIRATION/BIBLIOGRAPHY/Bibliography.md",
                "mode": "source",
                "source": false
              },
              "icon": "lucide-file",
              "title": "Bibliography"
            }
          }
        ]
      }
    ],
    "direction": "vertical"
  },
  "left": {
    "id": "3314960da67f7938",
    "type": "split",
    "children": [
      {
        "id": "1bf6b2707fdd0d52",
        "type": "tabs",
        "children": [
          {
            "id": "f6518dcf2b102103",
            "type": "leaf",
            "state": {
              "type": "file-explorer",
              "state": {
                "sortOrder": "alphabetical"
              },
              "icon": "lucide-folder-closed",
              "title": "Files"
            }
          },
          {
            "id": "299b826124a5a7cd",
            "type": "leaf",
            "state": {
              "type": "search",
              "state": {
                "query": "",
                "matchingCase": false,
                "explainSearch": false,
                "collapseAll": false,
                "extraContext": false,
                "sortOrder": "alphabetical"
              },
              "icon": "lucide-search",
              "title": "Search"
            }
          },
          {
            "id": "343d7f0d50594f91",
            "type": "leaf",
            "state": {
              "type": "bookmarks",
              "state": {},
              "icon": "lucide-bookmark",
              "title": "Bookmarks"
            }
          }
        ]
      }
    ],
    "direction": "horizontal",
    "width": 270.5
  },
  "right": {
    "id": "ca421a90d551bf28",
    "type": "split",
    "children": [
      {
        "id": "ca11bdfda62f5faf",
        "type": "tabs",
        "children": [
          {
            "id": "e90a4fd6213fd5de",
            "type": "leaf",
            "state": {
              "type": "backlink",
              "state": {
                "file": "README.md",
                "collapseAll": false,
                "extraContext": false,
                "sortOrder": "alphabetical",
                "showSearch": false,
                "searchQuery": "",
                "backlinkCollapsed": false,
                "unlinkedCollapsed": true
              },
              "icon": "links-coming-in",
              "title": "Backlinks for README"
            }
          },
          {
            "id": "55575a1286d071e5",
            "type": "leaf",
            "state": {
              "type": "outgoing-link",
              "state": {
                "file": "README.md",
                "linksCollapsed": false,
                "unlinkedCollapsed": true
              },
              "icon": "links-going-out",
              "title": "Outgoing links from README"
            }
          },
          {
            "id": "0e42f9e111ddc42e",
            "type": "leaf",
            "state": {
              "type": "tag",
              "state": {
                "sortOrder": "frequency",
                "useHierarchy": true
              },
              "icon": "lucide-tags",
              "title": "Tags"
            }
          },
          {
            "id": "55d3dd4255f9d19a",
            "type": "leaf",
            "state": {
              "type": "outline",
              "state": {
                "file": "README.md"
              },
              "icon": "lucide-list",
              "title": "Outline of README"
            }
          }
        ]
      }
    ],
    "direction": "horizontal",
    "width": 300,
    "collapsed": true
  },
  "left-ribbon": {
    "hiddenItems": {
      "switcher:Open quick switcher": false,
      "graph:Open graph view": false,
      "canvas:Create new canvas": false,
      "templates:Insert template": false,
      "command-palette:Open command palette": false
    }
  },
  "active": "3f276d0fd7dabbaa",
  "lastOpenFiles": [
    "A_INSPIRATION/BIBLIOGRAPHY/Bibliography.md",
    "D_OUTPUT/README.md",
    "B_METHOD/PROCESS/2024-10-03/Small_Presentation_of_Process.md",
    "README.md",
    "D_OUTPUT/PRACTICAL-PROJECT/Practical_Project_Ideas.md",
    "B_METHOD/PROCESS/2024-10-24/Thesis_Names.md",
    "B_METHOD/README.md",
    "B_METHOD/PROCESS/2024-10-24",
    "E_ASSETS/repo-images/skeuomorphism_subhero.png",
    "E_ASSETS/repo-images/SK_small.png",
    "D_OUTPUT/WRITING/2024-10-22/241022_Skeuomorphism.md",
    "D_OUTPUT/WRITING/2024-10-02/241002_Skeuomorphism.md",
    "D_OUTPUT/WRITING/2024-10-18/241018_Skeuomorphism.md",
    "D_OUTPUT/WRITING/2024-10-22/241018_Skeuomorphism.md",
    "D_OUTPUT/WRITING/2024-10-22",
    "D_OUTPUT/WRITING/2024-10-18 copy/241018_Skeuomorphism.md",
    "D_OUTPUT/WRITING/2024-10-18 copy",
    "D_OUTPUT/EXPORTS/241018_Skeuomorphism.pdf",
    "D_OUTPUT/WRITING/2024-10-18/241017_Skeuomorphism.md",
    "D_OUTPUT/WRITING/2024-10-18",
    "D_OUTPUT/WRITING/2024-10-17 - Copy/241017_Skeuomorphism.md",
    "D_OUTPUT/WRITING/2024-10-17 - Copy",
    "D_OUTPUT/WRITING/2024-10-17/241017_Skeuomorphism.md",
    "C_DATA/IMAGES/WindowsPhone7.jpg",
    "D_OUTPUT/WRITING/2024-10-16/241016_Skeuomorphism.md",
    "D_OUTPUT/WRITING/2024-10-17/241016_Skeuomorphism.md",
    "D_OUTPUT/WRITING/2024-10-17",
    "D_OUTPUT/WRITING/2024-10-16 - Copy/241016_Skeuomorphism.md",
    "D_OUTPUT/WRITING/2024-10-16 - Copy",
    "C_DATA/SPECTRUM/The_Spectrum_of_Skeuomorphic_GUIs_241001.canvas",
    "C_DATA/IMAGES/MacOSXCatalina_vs_MacOS11BigSur_FinderComparison.png",
    "C_DATA/IMAGES/Samsung_TouchWiz.png",
    "C_DATA/IMAGES/HTCSenseUI.jpg",
    "C_DATA/IMAGES/MacOSX_ContactsApp.png",
    "C_DATA/IMAGES/MacOSX_NotesApp.jpg",
    "C_DATA/IMAGES/MacOSX_Aqua_Pinstripes.png.~tmp",
    "C_DATA/IMAGES/MacOSX_Aqua_Pinstripes.png",
    "C_DATA/IMAGES/MacOSX_Aqua_Pinstripes.gif",
    "D_OUTPUT/WRITING/2024-10-16/241015_Skeuomorphism.md",
    "D_OUTPUT/WRITING/2024-10-16",
    "D_OUTPUT/WRITING/2024-10-15 - Copy/241015_Skeuomorphism.md",
    "D_OUTPUT/WRITING/2024-10-15/241015_Skeuomorphism.md",
    "D_OUTPUT/WRITING/2024-10-14/241014_Skeuomorphism.md",
    "D_OUTPUT/WRITING/2024-10-15/241014_Skeuomorphism.md",
    "D_OUTPUT/WRITING/2024-10-14 - Copy/241014_Skeuomorphism.md",
    "D_OUTPUT/WRITING/2024-10-11/241010_Skeuomorphism.md",
    "D_OUTPUT/WRITING/2024-10-10 - Copy/241010_Skeuomorphism.md",
    "B_METHOD/Methodology_Canvas-2024-09-30.canvas",
    "B_METHOD/Methodology_Canvas-2024-09-03.canvas",
    "Untitled.canvas",
    "Untitled 1.canvas"
  ]
}